trio_protocol/__init__.py
trio_protocol/loop.py
trio_protocol/server.py
trio_protocol/transport.py
trio_protocol-0.1.dist-info/METADATA
trio_protocol-0.1.dist-info/RECORD
trio_protocol-0.1.dist-info/WHEEL
trio_protocol-0.1.dist-info/top_level.txt
