Metadata-Version: 2.1
Name: trio-protocol
Version: 0.1
Summary: Trio implementation of asyncio.Protocol
Home-page: https://github.com/miracle2k/trio-protocol
Author: Michael Elsdorfer
Author-email: michael@elsdorfer.com
License: BSD
Platform: UNKNOWN
Classifier: Development Status :: 3 - Alpha
Classifier: Environment :: Web Environment
Classifier: Intended Audience :: Developers
Classifier: License :: OSI Approved :: BSD License
Classifier: Operating System :: OS Independent
Classifier: Topic :: Internet :: WWW/HTTP
Classifier: Programming Language :: Python :: 3
Classifier: Programming Language :: Python :: 3.5
Classifier: Programming Language :: Python :: 3.6
Classifier: Programming Language :: Python :: 3.7
